{
  "timestamp": "2026-06-12 13:48:35",
  "date": "2026-06-12",
  "market": {
    "price": 4041.9,
    "change_pct": 1.38,
    "volume": 12052.1
  },
  "emotion": {
    "score": 85,
    "phase": "主升浪・强一致",
    "position": "8-10成",
    "detail": {
      "blast_rate": 35.2,
      "prev_connect_pct": 2.4,
      "noodle_count": 0,
      "promotion_rate": 0,
      "zt_count": 94,
      "dt_count": 9,
      "zb_count": 51,
      "lb_count": 178
    }
  },
  "core": {
    "blast_rate": 35.2,
    "prev_connect_pct": 2.4,
    "noodle_count": 0,
    "promotion_rate": 0
  },
  "ladder": {
    "max_board": 1,
    "stocks": [
      {
        "code": "301323",
        "name": "新莱福",
        "change_pct": 20.0,
        "board": 1,
        "turnover": 8.63,
        "first_time": "",
        "amount": 5.73,
        "style": "换手"
      },
      {
        "code": "301176",
        "name": "逸豪新材",
        "change_pct": 19.99,
        "board": 1,
        "turnover": 8.57,
        "first_time": "",
        "amount": 7.39,
        "style": "换手"
      },
      {
        "code": "688010",
        "name": "福光股份",
        "change_pct": 19.99,
        "board": 1,
        "turnover": 13.75,
        "first_time": "",
        "amount": 9.99,
        "style": "换手"
      },
      {
        "code": "688662",
        "name": "富信科技",
        "change_pct": 19.45,
        "board": 1,
        "turnover": 18.3,
        "first_time": "",
        "amount": 23.9,
        "style": "换手"
      },
      {
        "code": "688772",
        "name": "珠海冠宇",
        "change_pct": 15.19,
        "board": 1,
        "turnover": 9.44,
        "first_time": "",
        "amount": 19.28,
        "style": "换手"
      },
      {
        "code": "300566",
        "name": "激智科技",
        "change_pct": 12.59,
        "board": 1,
        "turnover": 17.85,
        "first_time": "",
        "amount": 12.34,
        "style": "换手"
      },
      {
        "code": "300263",
        "name": "隆华科技",
        "change_pct": 11.71,
        "board": 1,
        "turnover": 22.32,
        "first_time": "",
        "amount": 34.4,
        "style": "换手"
      },
      {
        "code": "688388",
        "name": "嘉元科技",
        "change_pct": 11.06,
        "board": 1,
        "turnover": 11.42,
        "first_time": "",
        "amount": 29.5,
        "style": "换手"
      },
      {
        "code": "600067",
        "name": "冠城新材",
        "change_pct": 10.13,
        "board": 1,
        "turnover": 7.7,
        "first_time": "",
        "amount": 3.59,
        "style": "换手"
      },
      {
        "code": "603020",
        "name": "爱普股份",
        "change_pct": 10.04,
        "board": 1,
        "turnover": 5.64,
        "first_time": "",
        "amount": 2.7,
        "style": "换手"
      },
      {
        "code": "603065",
        "name": "宿迁联盛",
        "change_pct": 10.03,
        "board": 1,
        "turnover": 1.86,
        "first_time": "",
        "amount": 1.06,
        "style": "换手"
      },
      {
        "code": "001696",
        "name": "宗申动力",
        "change_pct": 10.02,
        "board": 1,
        "turnover": 10.24,
        "first_time": "",
        "amount": 20.52,
        "style": "换手"
      },
      {
        "code": "603120",
        "name": "肯特催化",
        "change_pct": 10.0,
        "board": 1,
        "turnover": 24.47,
        "first_time": "",
        "amount": 5.26,
        "style": "换手"
      },
      {
        "code": "002976",
        "name": "瑞玛精密",
        "change_pct": 10.0,
        "board": 1,
        "turnover": 5.84,
        "first_time": "",
        "amount": 1.27,
        "style": "换手"
      },
      {
        "code": "000759",
        "name": "中百集团",
        "change_pct": 10.0,
        "board": 1,
        "turnover": 14.12,
        "first_time": "",
        "amount": 5.02,
        "style": "换手"
      },
      {
        "code": "601958",
        "name": "金钼股份",
        "change_pct": 10.0,
        "board": 1,
        "turnover": 0.38,
        "first_time": "",
        "amount": 3.13,
        "style": "一字"
      },
      {
        "code": "003009",
        "name": "中天火箭",
        "change_pct": 10.0,
        "board": 1,
        "turnover": 3.27,
        "first_time": "",
        "amount": 3.18,
        "style": "换手"
      },
      {
        "code": "603014",
        "name": "威高血净",
        "change_pct": 10.0,
        "board": 1,
        "turnover": 8.69,
        "first_time": "",
        "amount": 3.15,
        "style": "换手"
      },
      {
        "code": "002203",
        "name": "海亮股份",
        "change_pct": 10.0,
        "board": 1,
        "turnover": 4.12,
        "first_time": "",
        "amount": 21.31,
        "style": "换手"
      },
      {
        "code": "000510",
        "name": "新金路",
        "change_pct": 9.99,
        "board": 1,
        "turnover": 10.95,
        "first_time": "",
        "amount": 12.6,
        "style": "换手"
      },
      {
        "code": "001257",
        "name": "盛龙股份",
        "change_pct": 9.99,
        "board": 1,
        "turnover": 10.16,
        "first_time": "",
        "amount": 3.86,
        "style": "换手"
      },
      {
        "code": "600500",
        "name": "中化国际",
        "change_pct": 9.99,
        "board": 1,
        "turnover": 13.3,
        "first_time": "",
        "amount": 37.72,
        "style": "换手"
      },
      {
        "code": "002830",
        "name": "名雕股份",
        "change_pct": 9.97,
        "board": 1,
        "turnover": 6.23,
        "first_time": "",
        "amount": 0.94,
        "style": "换手"
      },
      {
        "code": "603335",
        "name": "迪生力",
        "change_pct": 9.97,
        "board": 1,
        "turnover": 1.2,
        "first_time": "",
        "amount": 0.41,
        "style": "换手"
      },
      {
        "code": "600229",
        "name": "城市传媒",
        "change_pct": 9.95,
        "board": 1,
        "turnover": 5.03,
        "first_time": "",
        "amount": 1.95,
        "style": "换手"
      },
      {
        "code": "301217",
        "name": "铜冠铜箔",
        "change_pct": 9.35,
        "board": 1,
        "turnover": 4.39,
        "first_time": "",
        "amount": 51.13,
        "style": "换手"
      },
      {
        "code": "301377",
        "name": "鼎泰高科",
        "change_pct": 9.28,
        "board": 1,
        "turnover": 4.72,
        "first_time": "",
        "amount": 21.59,
        "style": "换手"
      },
      {
        "code": "300706",
        "name": "阿石创",
        "change_pct": 9.15,
        "board": 1,
        "turnover": 31.7,
        "first_time": "",
        "amount": 26.45,
        "style": "换手"
      },
      {
        "code": "300586",
        "name": "美联新材",
        "change_pct": 8.77,
        "board": 1,
        "turnover": 12.3,
        "first_time": "",
        "amount": 8.88,
        "style": "换手"
      },
      {
        "code": "300234",
        "name": "开尔新材",
        "change_pct": 8.74,
        "board": 1,
        "turnover": 9.99,
        "first_time": "",
        "amount": 3.52,
        "style": "换手"
      },
      {
        "code": "301526",
        "name": "国际复材",
        "change_pct": 8.7,
        "board": 1,
        "turnover": 13.07,
        "first_time": "",
        "amount": 52.47,
        "style": "换手"
      },
      {
        "code": "688323",
        "name": "瑞华泰",
        "change_pct": 8.47,
        "board": 1,
        "turnover": 11.43,
        "first_time": "",
        "amount": 8.88,
        "style": "换手"
      },
      {
        "code": "920015",
        "name": "锦华新材",
        "change_pct": 8.37,
        "board": 1,
        "turnover": 19.36,
        "first_time": "",
        "amount": 4.06,
        "style": "换手"
      },
      {
        "code": "002971",
        "name": "和远气体",
        "change_pct": 8.25,
        "board": 1,
        "turnover": 33.22,
        "first_time": "",
        "amount": 29.91,
        "style": "换手"
      },
      {
        "code": "688020",
        "name": "方邦股份",
        "change_pct": 8.14,
        "board": 1,
        "turnover": 7.87,
        "first_time": "",
        "amount": 12.81,
        "style": "换手"
      },
      {
        "code": "688082",
        "name": "盛美上海",
        "change_pct": 7.65,
        "board": 1,
        "turnover": 2.54,
        "first_time": "",
        "amount": 37.87,
        "style": "换手"
      },
      {
        "code": "300054",
        "name": "鼎龙股份",
        "change_pct": 7.64,
        "board": 1,
        "turnover": 9.89,
        "first_time": "",
        "amount": 62.19,
        "style": "换手"
      },
      {
        "code": "688233",
        "name": "神工股份",
        "change_pct": 7.49,
        "board": 1,
        "turnover": 12.13,
        "first_time": "",
        "amount": 23.33,
        "style": "换手"
      },
      {
        "code": "600110",
        "name": "诺德股份",
        "change_pct": 7.28,
        "board": 1,
        "turnover": 13.23,
        "first_time": "",
        "amount": 29.76,
        "style": "换手"
      },
      {
        "code": "300353",
        "name": "东土科技",
        "change_pct": 6.83,
        "board": 1,
        "turnover": 8.09,
        "first_time": "",
        "amount": 9.65,
        "style": "换手"
      },
      {
        "code": "688257",
        "name": "新锐股份",
        "change_pct": 6.45,
        "board": 1,
        "turnover": 6.3,
        "first_time": "",
        "amount": 18.58,
        "style": "换手"
      },
      {
        "code": "300570",
        "name": "太辰光",
        "change_pct": 6.37,
        "board": 1,
        "turnover": 16.92,
        "first_time": "",
        "amount": 59.76,
        "style": "换手"
      },
      {
        "code": "688300",
        "name": "联瑞新材",
        "change_pct": 6.36,
        "board": 1,
        "turnover": 3.87,
        "first_time": "",
        "amount": 18.56,
        "style": "换手"
      },
      {
        "code": "301568",
        "name": "思泰克",
        "change_pct": 5.93,
        "board": 1,
        "turnover": 12.19,
        "first_time": "",
        "amount": 5.22,
        "style": "换手"
      },
      {
        "code": "605186",
        "name": "健麾信息",
        "change_pct": 5.91,
        "board": 1,
        "turnover": 8.67,
        "first_time": "",
        "amount": 4.09,
        "style": "换手"
      },
      {
        "code": "603733",
        "name": "仙鹤股份",
        "change_pct": 5.9,
        "board": 1,
        "turnover": 3.8,
        "first_time": "",
        "amount": 7.78,
        "style": "换手"
      },
      {
        "code": "688525",
        "name": "佰维存储",
        "change_pct": 5.82,
        "board": 1,
        "turnover": 8.85,
        "first_time": "",
        "amount": 145.1,
        "style": "换手"
      },
      {
        "code": "002842",
        "name": "翔鹭钨业",
        "change_pct": 5.8,
        "board": 1,
        "turnover": 37.98,
        "first_time": "",
        "amount": 41.21,
        "style": "换手"
      },
      {
        "code": "002636",
        "name": "金安国纪",
        "change_pct": 5.78,
        "board": 1,
        "turnover": 9.06,
        "first_time": "",
        "amount": 59.19,
        "style": "换手"
      },
      {
        "code": "002119",
        "name": "康强电子",
        "change_pct": 5.67,
        "board": 1,
        "turnover": 30.61,
        "first_time": "",
        "amount": 38.07,
        "style": "换手"
      },
      {
        "code": "301107",
        "name": "瑜欣电子",
        "change_pct": 5.59,
        "board": 1,
        "turnover": 11.74,
        "first_time": "",
        "amount": 2.45,
        "style": "换手"
      },
      {
        "code": "603608",
        "name": "天创时尚",
        "change_pct": 5.56,
        "board": 1,
        "turnover": 9.76,
        "first_time": "",
        "amount": 10.42,
        "style": "换手"
      },
      {
        "code": "688147",
        "name": "微导纳米",
        "change_pct": 5.36,
        "board": 1,
        "turnover": 5.22,
        "first_time": "",
        "amount": 23.48,
        "style": "换手"
      },
      {
        "code": "000831",
        "name": "中国稀土",
        "change_pct": 5.32,
        "board": 1,
        "turnover": 7.18,
        "first_time": "",
        "amount": 43.17,
        "style": "换手"
      },
      {
        "code": "002955",
        "name": "鸿合科技",
        "change_pct": 5.24,
        "board": 1,
        "turnover": 6.78,
        "first_time": "",
        "amount": 4.26,
        "style": "换手"
      },
      {
        "code": "000657",
        "name": "中钨高新",
        "change_pct": 5.14,
        "board": 1,
        "turnover": 8.61,
        "first_time": "",
        "amount": 100.31,
        "style": "换手"
      },
      {
        "code": "688059",
        "name": "华锐精密",
        "change_pct": 4.91,
        "board": 1,
        "turnover": 4.08,
        "first_time": "",
        "amount": 7.04,
        "style": "换手"
      },
      {
        "code": "688332",
        "name": "中科蓝讯",
        "change_pct": 4.84,
        "board": 1,
        "turnover": 4.13,
        "first_time": "",
        "amount": 7.41,
        "style": "换手"
      },
      {
        "code": "688409",
        "name": "富创精密",
        "change_pct": 4.81,
        "board": 1,
        "turnover": 4.54,
        "first_time": "",
        "amount": 26.47,
        "style": "换手"
      },
      {
        "code": "300720",
        "name": "海川智能",
        "change_pct": 4.77,
        "board": 1,
        "turnover": 6.44,
        "first_time": "",
        "amount": 9.2,
        "style": "换手"
      },
      {
        "code": "002718",
        "name": "友邦吊顶",
        "change_pct": 4.66,
        "board": 1,
        "turnover": 2.33,
        "first_time": "",
        "amount": 2.22,
        "style": "换手"
      },
      {
        "code": "300331",
        "name": "苏大维格",
        "change_pct": 4.66,
        "board": 1,
        "turnover": 10.8,
        "first_time": "",
        "amount": 15.97,
        "style": "换手"
      },
      {
        "code": "600160",
        "name": "巨化股份",
        "change_pct": 4.51,
        "board": 1,
        "turnover": 3.55,
        "first_time": "",
        "amount": 40.39,
        "style": "换手"
      },
      {
        "code": "600498",
        "name": "烽火通信",
        "change_pct": 4.49,
        "board": 1,
        "turnover": 14.47,
        "first_time": "",
        "amount": 117.59,
        "style": "换手"
      },
      {
        "code": "002171",
        "name": "楚江新材",
        "change_pct": 4.27,
        "board": 1,
        "turnover": 7.82,
        "first_time": "",
        "amount": 16.84,
        "style": "换手"
      },
      {
        "code": "000920",
        "name": "沃顿科技",
        "change_pct": 4.12,
        "board": 1,
        "turnover": 5.7,
        "first_time": "",
        "amount": 3.75,
        "style": "换手"
      },
      {
        "code": "603257",
        "name": "中国瑞林",
        "change_pct": 4.04,
        "board": 1,
        "turnover": 10.69,
        "first_time": "",
        "amount": 1.83,
        "style": "换手"
      },
      {
        "code": "300334",
        "name": "津膜科技",
        "change_pct": 3.97,
        "board": 1,
        "turnover": 14.76,
        "first_time": "",
        "amount": 5.75,
        "style": "换手"
      },
      {
        "code": "002057",
        "name": "中钢天源",
        "change_pct": 3.96,
        "board": 1,
        "turnover": 9.56,
        "first_time": "",
        "amount": 8.72,
        "style": "换手"
      },
      {
        "code": "603283",
        "name": "赛腾股份",
        "change_pct": 3.75,
        "board": 1,
        "turnover": 10.11,
        "first_time": "",
        "amount": 19.41,
        "style": "换手"
      },
      {
        "code": "300894",
        "name": "火星人",
        "change_pct": 3.69,
        "board": 1,
        "turnover": 9.9,
        "first_time": "",
        "amount": 3.41,
        "style": "换手"
      },
      {
        "code": "600176",
        "name": "中国巨石",
        "change_pct": 3.65,
        "board": 1,
        "turnover": 3.99,
        "first_time": "",
        "amount": 68.59,
        "style": "换手"
      },
      {
        "code": "002832",
        "name": "比音勒芬",
        "change_pct": 3.53,
        "board": 1,
        "turnover": 3.72,
        "first_time": "",
        "amount": 3.01,
        "style": "换手"
      },
      {
        "code": "300307",
        "name": "慈星股份",
        "change_pct": 3.48,
        "board": 1,
        "turnover": 6.31,
        "first_time": "",
        "amount": 3.87,
        "style": "换手"
      },
      {
        "code": "605318",
        "name": "法狮龙",
        "change_pct": 3.15,
        "board": 1,
        "turnover": 5.35,
        "first_time": "",
        "amount": 8.85,
        "style": "换手"
      },
      {
        "code": "003036",
        "name": "泰坦股份",
        "change_pct": 3.04,
        "board": 1,
        "turnover": 4.68,
        "first_time": "",
        "amount": 8.35,
        "style": "换手"
      },
      {
        "code": "301511",
        "name": "德福科技",
        "change_pct": 3.03,
        "board": 1,
        "turnover": 8.69,
        "first_time": "",
        "amount": 46.1,
        "style": "换手"
      },
      {
        "code": "300786",
        "name": "国林科技",
        "change_pct": 3.0,
        "board": 1,
        "turnover": 12.86,
        "first_time": "",
        "amount": 4.03,
        "style": "换手"
      },
      {
        "code": "600345",
        "name": "长江通信",
        "change_pct": 2.98,
        "board": 1,
        "turnover": 11.23,
        "first_time": "",
        "amount": 14.27,
        "style": "换手"
      },
      {
        "code": "600593",
        "name": "大连圣亚",
        "change_pct": 2.88,
        "board": 1,
        "turnover": 5.91,
        "first_time": "",
        "amount": 3.05,
        "style": "换手"
      },
      {
        "code": "300260",
        "name": "新莱应材",
        "change_pct": 2.76,
        "board": 1,
        "turnover": 11.05,
        "first_time": "",
        "amount": 24.9,
        "style": "换手"
      },
      {
        "code": "603976",
        "name": "正川股份",
        "change_pct": 2.72,
        "board": 1,
        "turnover": 4.12,
        "first_time": "",
        "amount": 1.58,
        "style": "换手"
      },
      {
        "code": "603060",
        "name": "国检集团",
        "change_pct": 2.27,
        "board": 1,
        "turnover": 4.24,
        "first_time": "",
        "amount": 2.64,
        "style": "换手"
      },
      {
        "code": "688630",
        "name": "芯碁微装",
        "change_pct": 2.13,
        "board": 1,
        "turnover": 4.63,
        "first_time": "",
        "amount": 25.38,
        "style": "换手"
      },
      {
        "code": "002965",
        "name": "祥鑫科技",
        "change_pct": 2.1,
        "board": 1,
        "turnover": 14.62,
        "first_time": "",
        "amount": 11.29,
        "style": "换手"
      },
      {
        "code": "000048",
        "name": "京基智农",
        "change_pct": 1.94,
        "board": 1,
        "turnover": 12.7,
        "first_time": "",
        "amount": 13.64,
        "style": "换手"
      },
      {
        "code": "688218",
        "name": "江苏北人",
        "change_pct": 1.84,
        "board": 1,
        "turnover": 5.27,
        "first_time": "",
        "amount": 3.37,
        "style": "换手"
      },
      {
        "code": "002129",
        "name": "TCL中环",
        "change_pct": 1.78,
        "board": 1,
        "turnover": 9.83,
        "first_time": "",
        "amount": 42.53,
        "style": "换手"
      },
      {
        "code": "300976",
        "name": "达瑞电子",
        "change_pct": 1.77,
        "board": 1,
        "turnover": 7.19,
        "first_time": "",
        "amount": 6.23,
        "style": "换手"
      },
      {
        "code": "603150",
        "name": "万朗磁塑",
        "change_pct": 1.63,
        "board": 1,
        "turnover": 2.96,
        "first_time": "",
        "amount": 1.97,
        "style": "换手"
      },
      {
        "code": "002937",
        "name": "兴瑞科技",
        "change_pct": 1.62,
        "board": 1,
        "turnover": 4.84,
        "first_time": "",
        "amount": 5.73,
        "style": "换手"
      },
      {
        "code": "603823",
        "name": "百合花",
        "change_pct": 1.6,
        "board": 1,
        "turnover": 5.72,
        "first_time": "",
        "amount": 9.85,
        "style": "换手"
      },
      {
        "code": "601166",
        "name": "XD兴业银",
        "change_pct": 1.59,
        "board": 1,
        "turnover": 0.52,
        "first_time": "",
        "amount": 20.43,
        "style": "换手"
      },
      {
        "code": "603324",
        "name": "盛剑科技",
        "change_pct": 1.57,
        "board": 1,
        "turnover": 10.28,
        "first_time": "",
        "amount": 5.41,
        "style": "换手"
      },
      {
        "code": "600183",
        "name": "生益科技",
        "change_pct": 1.56,
        "board": 1,
        "turnover": 3.22,
        "first_time": "",
        "amount": 120.53,
        "style": "换手"
      },
      {
        "code": "603186",
        "name": "华正新材",
        "change_pct": 1.5,
        "board": 1,
        "turnover": 11.34,
        "first_time": "",
        "amount": 31.98,
        "style": "换手"
      },
      {
        "code": "601838",
        "name": "成都银行",
        "change_pct": 1.47,
        "board": 1,
        "turnover": 0.61,
        "first_time": "",
        "amount": 5.15,
        "style": "换手"
      },
      {
        "code": "300825",
        "name": "阿尔特",
        "change_pct": 1.39,
        "board": 1,
        "turnover": 7.25,
        "first_time": "",
        "amount": 5.32,
        "style": "换手"
      },
      {
        "code": "301072",
        "name": "中捷精工",
        "change_pct": 1.37,
        "board": 1,
        "turnover": 7.05,
        "first_time": "",
        "amount": 1.7,
        "style": "换手"
      },
      {
        "code": "603303",
        "name": "XD得邦照",
        "change_pct": 1.09,
        "board": 1,
        "turnover": 2.45,
        "first_time": "",
        "amount": 3.87,
        "style": "换手"
      },
      {
        "code": "688605",
        "name": "先锋精科",
        "change_pct": 1.06,
        "board": 1,
        "turnover": 9.32,
        "first_time": "",
        "amount": 8.68,
        "style": "换手"
      },
      {
        "code": "600459",
        "name": "贵研铂业",
        "change_pct": 1.04,
        "board": 1,
        "turnover": 11.24,
        "first_time": "",
        "amount": 21.89,
        "style": "换手"
      },
      {
        "code": "688598",
        "name": "金博股份",
        "change_pct": 1.01,
        "board": 1,
        "turnover": 10.92,
        "first_time": "",
        "amount": 8.15,
        "style": "换手"
      },
      {
        "code": "688545",
        "name": "XD兴福电",
        "change_pct": 1.01,
        "board": 1,
        "turnover": 14.96,
        "first_time": "",
        "amount": 28.89,
        "style": "换手"
      },
      {
        "code": "600900",
        "name": "长江电力",
        "change_pct": 0.9,
        "board": 1,
        "turnover": 0.39,
        "first_time": "",
        "amount": 26.85,
        "style": "一字"
      },
      {
        "code": "002409",
        "name": "雅克科技",
        "change_pct": 0.89,
        "board": 1,
        "turnover": 16.6,
        "first_time": "",
        "amount": 73.41,
        "style": "换手"
      },
      {
        "code": "603256",
        "name": "宏和科技",
        "change_pct": 0.77,
        "board": 1,
        "turnover": 1.68,
        "first_time": "",
        "amount": 31.91,
        "style": "换手"
      },
      {
        "code": "688383",
        "name": "新益昌",
        "change_pct": 0.6,
        "board": 1,
        "turnover": 3.05,
        "first_time": "",
        "amount": 4.93,
        "style": "换手"
      },
      {
        "code": "600919",
        "name": "江苏银行",
        "change_pct": 0.59,
        "board": 1,
        "turnover": 0.4,
        "first_time": "",
        "amount": 8.66,
        "style": "一字"
      },
      {
        "code": "601939",
        "name": "建设银行",
        "change_pct": 0.57,
        "board": 1,
        "turnover": 0.89,
        "first_time": "",
        "amount": 9.01,
        "style": "换手"
      },
      {
        "code": "000691",
        "name": "亚太实业",
        "change_pct": 0.5,
        "board": 1,
        "turnover": 5.03,
        "first_time": "",
        "amount": 1.63,
        "style": "换手"
      },
      {
        "code": "301617",
        "name": "博苑新材",
        "change_pct": 0.47,
        "board": 1,
        "turnover": 5.03,
        "first_time": "",
        "amount": 1.91,
        "style": "换手"
      },
      {
        "code": "603124",
        "name": "江南新材",
        "change_pct": 0.45,
        "board": 1,
        "turnover": 5.8,
        "first_time": "",
        "amount": 8.21,
        "style": "换手"
      },
      {
        "code": "688809",
        "name": "强一股份",
        "change_pct": 0.31,
        "board": 1,
        "turnover": 14.56,
        "first_time": "",
        "amount": 20.93,
        "style": "换手"
      },
      {
        "code": "605566",
        "name": "福莱蒽特",
        "change_pct": 0.17,
        "board": 1,
        "turnover": 5.43,
        "first_time": "",
        "amount": 3.41,
        "style": "换手"
      },
      {
        "code": "300700",
        "name": "岱勒新材",
        "change_pct": 0.0,
        "board": 1,
        "turnover": 5.66,
        "first_time": "",
        "amount": 3.51,
        "style": "换手"
      },
      {
        "code": "600549",
        "name": "厦门钨业",
        "change_pct": 0.0,
        "board": 1,
        "turnover": 8.06,
        "first_time": "",
        "amount": 85.1,
        "style": "换手"
      },
      {
        "code": "000921",
        "name": "海信家电",
        "change_pct": -0.1,
        "board": 1,
        "turnover": 4.29,
        "first_time": "",
        "amount": 11.66,
        "style": "换手"
      },
      {
        "code": "300747",
        "name": "锐科激光",
        "change_pct": -0.25,
        "board": 1,
        "turnover": 10.23,
        "first_time": "",
        "amount": 26.96,
        "style": "换手"
      },
      {
        "code": "301389",
        "name": "隆扬电子",
        "change_pct": -0.41,
        "board": 1,
        "turnover": 5.87,
        "first_time": "",
        "amount": 15.79,
        "style": "换手"
      },
      {
        "code": "688498",
        "name": "源杰科技",
        "change_pct": -0.42,
        "board": 1,
        "turnover": 5.32,
        "first_time": "",
        "amount": 96.78,
        "style": "换手"
      },
      {
        "code": "601208",
        "name": "东材科技",
        "change_pct": -0.42,
        "board": 1,
        "turnover": 10.03,
        "first_time": "",
        "amount": 63.98,
        "style": "换手"
      },
      {
        "code": "688627",
        "name": "精智达",
        "change_pct": -0.52,
        "board": 1,
        "turnover": 8.67,
        "first_time": "",
        "amount": 27.45,
        "style": "换手"
      },
      {
        "code": "688733",
        "name": "壹石通",
        "change_pct": -0.57,
        "board": 1,
        "turnover": 10.79,
        "first_time": "",
        "amount": 9.04,
        "style": "换手"
      },
      {
        "code": "003043",
        "name": "华亚智能",
        "change_pct": -0.59,
        "board": 1,
        "turnover": 7.95,
        "first_time": "",
        "amount": 5.49,
        "style": "换手"
      },
      {
        "code": "000029",
        "name": "深深房Ａ",
        "change_pct": -0.67,
        "board": 1,
        "turnover": 0.78,
        "first_time": "",
        "amount": 1.78,
        "style": "换手"
      },
      {
        "code": "688669",
        "name": "聚石化学",
        "change_pct": -0.97,
        "board": 1,
        "turnover": 3.59,
        "first_time": "",
        "amount": 2.09,
        "style": "换手"
      },
      {
        "code": "688519",
        "name": "南亚新材",
        "change_pct": -1.02,
        "board": 1,
        "turnover": 2.98,
        "first_time": "",
        "amount": 22.31,
        "style": "换手"
      },
      {
        "code": "601137",
        "name": "博威合金",
        "change_pct": -1.05,
        "board": 1,
        "turnover": 5.71,
        "first_time": "",
        "amount": 12.84,
        "style": "换手"
      },
      {
        "code": "300951",
        "name": "博硕科技",
        "change_pct": -1.05,
        "board": 1,
        "turnover": 1.85,
        "first_time": "",
        "amount": 1.23,
        "style": "换手"
      },
      {
        "code": "300554",
        "name": "三超新材",
        "change_pct": -1.06,
        "board": 1,
        "turnover": 10.8,
        "first_time": "",
        "amount": 2.58,
        "style": "换手"
      },
      {
        "code": "300656",
        "name": "民德电子",
        "change_pct": -1.11,
        "board": 1,
        "turnover": 7.16,
        "first_time": "",
        "amount": 3.59,
        "style": "换手"
      },
      {
        "code": "688783",
        "name": "西安奕材-U",
        "change_pct": -1.21,
        "board": 1,
        "turnover": 28.01,
        "first_time": "",
        "amount": 26.29,
        "style": "换手"
      },
      {
        "code": "002165",
        "name": "红 宝 丽",
        "change_pct": -1.25,
        "board": 1,
        "turnover": 19.72,
        "first_time": "",
        "amount": 11.03,
        "style": "换手"
      },
      {
        "code": "603002",
        "name": "XD宏昌电",
        "change_pct": -1.34,
        "board": 1,
        "turnover": 7.13,
        "first_time": "",
        "amount": 14.58,
        "style": "换手"
      },
      {
        "code": "600228",
        "name": "返利科技",
        "change_pct": -1.48,
        "board": 1,
        "turnover": 8.18,
        "first_time": "",
        "amount": 2.46,
        "style": "换手"
      },
      {
        "code": "688661",
        "name": "和林微纳",
        "change_pct": -1.94,
        "board": 1,
        "turnover": 4.9,
        "first_time": "",
        "amount": 10.17,
        "style": "换手"
      },
      {
        "code": "688138",
        "name": "清溢光电",
        "change_pct": -1.96,
        "board": 1,
        "turnover": 7.27,
        "first_time": "",
        "amount": 8.53,
        "style": "换手"
      },
      {
        "code": "600665",
        "name": "天地源",
        "change_pct": -1.97,
        "board": 1,
        "turnover": 9.32,
        "first_time": "",
        "amount": 3.16,
        "style": "换手"
      },
      {
        "code": "300666",
        "name": "江丰电子",
        "change_pct": -1.98,
        "board": 1,
        "turnover": 16.39,
        "first_time": "",
        "amount": 108.69,
        "style": "换手"
      },
      {
        "code": "603330",
        "name": "天洋新材",
        "change_pct": -2.04,
        "board": 1,
        "turnover": 10.22,
        "first_time": "",
        "amount": 3.61,
        "style": "换手"
      },
      {
        "code": "600667",
        "name": "太极实业",
        "change_pct": -2.11,
        "board": 1,
        "turnover": 16.84,
        "first_time": "",
        "amount": 62.23,
        "style": "换手"
      },
      {
        "code": "603663",
        "name": "三祥新材",
        "change_pct": -2.22,
        "board": 1,
        "turnover": 5.3,
        "first_time": "",
        "amount": 16.95,
        "style": "换手"
      },
      {
        "code": "688456",
        "name": "有研粉材",
        "change_pct": -2.3,
        "board": 1,
        "turnover": 13.26,
        "first_time": "",
        "amount": 18.32,
        "style": "换手"
      },
      {
        "code": "301161",
        "name": "唯万密封",
        "change_pct": -2.3,
        "board": 1,
        "turnover": 19.98,
        "first_time": "",
        "amount": 5.75,
        "style": "换手"
      },
      {
        "code": "002815",
        "name": "崇达技术",
        "change_pct": -2.37,
        "board": 1,
        "turnover": 10.85,
        "first_time": "",
        "amount": 15.05,
        "style": "换手"
      },
      {
        "code": "000823",
        "name": "超声电子",
        "change_pct": -2.51,
        "board": 1,
        "turnover": 17.44,
        "first_time": "",
        "amount": 20.08,
        "style": "换手"
      },
      {
        "code": "300936",
        "name": "中英科技",
        "change_pct": -2.69,
        "board": 1,
        "turnover": 9.01,
        "first_time": "",
        "amount": 4.88,
        "style": "换手"
      },
      {
        "code": "920489",
        "name": "佳先股份",
        "change_pct": -2.74,
        "board": 1,
        "turnover": 7.3,
        "first_time": "",
        "amount": 1.05,
        "style": "换手"
      },
      {
        "code": "300557",
        "name": "理工光科",
        "change_pct": -2.78,
        "board": 1,
        "turnover": 6.86,
        "first_time": "",
        "amount": 3.38,
        "style": "换手"
      },
      {
        "code": "600178",
        "name": "东安动力",
        "change_pct": -2.84,
        "board": 1,
        "turnover": 6.7,
        "first_time": "",
        "amount": 3.36,
        "style": "换手"
      },
      {
        "code": "603203",
        "name": "快克智能",
        "change_pct": -3.06,
        "board": 1,
        "turnover": 7.09,
        "first_time": "",
        "amount": 13.82,
        "style": "换手"
      },
      {
        "code": "605589",
        "name": "XD圣泉集",
        "change_pct": -3.18,
        "board": 1,
        "turnover": 11.12,
        "first_time": "",
        "amount": 56.28,
        "style": "换手"
      },
      {
        "code": "600206",
        "name": "有研新材",
        "change_pct": -3.68,
        "board": 1,
        "turnover": 18.29,
        "first_time": "",
        "amount": 53.09,
        "style": "换手"
      },
      {
        "code": "600353",
        "name": "旭光电子",
        "change_pct": -3.71,
        "board": 1,
        "turnover": 12.13,
        "first_time": "",
        "amount": 30.53,
        "style": "换手"
      },
      {
        "code": "603135",
        "name": "中重科技",
        "change_pct": -4.3,
        "board": 1,
        "turnover": 6.43,
        "first_time": "",
        "amount": 5.07,
        "style": "换手"
      },
      {
        "code": "003026",
        "name": "中晶科技",
        "change_pct": -4.32,
        "board": 1,
        "turnover": 18.62,
        "first_time": "",
        "amount": 9.47,
        "style": "换手"
      },
      {
        "code": "300093",
        "name": "金刚光伏",
        "change_pct": -4.35,
        "board": 1,
        "turnover": 6.37,
        "first_time": "",
        "amount": 3.41,
        "style": "换手"
      },
      {
        "code": "603929",
        "name": "亚翔集成",
        "change_pct": -4.57,
        "board": 1,
        "turnover": 4.2,
        "first_time": "",
        "amount": 20.68,
        "style": "换手"
      },
      {
        "code": "002254",
        "name": "泰和新材",
        "change_pct": -4.6,
        "board": 1,
        "turnover": 13.92,
        "first_time": "",
        "amount": 20.91,
        "style": "换手"
      },
      {
        "code": "603688",
        "name": "石英股份",
        "change_pct": -4.69,
        "board": 1,
        "turnover": 8.77,
        "first_time": "",
        "amount": 36.41,
        "style": "换手"
      },
      {
        "code": "301228",
        "name": "实朴检测",
        "change_pct": -4.75,
        "board": 1,
        "turnover": 4.63,
        "first_time": "",
        "amount": 4.45,
        "style": "换手"
      },
      {
        "code": "688359",
        "name": "三孚新科",
        "change_pct": -4.75,
        "board": 1,
        "turnover": 4.27,
        "first_time": "",
        "amount": 6.18,
        "style": "换手"
      },
      {
        "code": "605358",
        "name": "立昂微",
        "change_pct": -5.1,
        "board": 1,
        "turnover": 11.34,
        "first_time": "",
        "amount": 59.93,
        "style": "换手"
      },
      {
        "code": "300821",
        "name": "东岳硅材",
        "change_pct": -5.6,
        "board": 1,
        "turnover": 7.35,
        "first_time": "",
        "amount": 15.48,
        "style": "换手"
      },
      {
        "code": "605006",
        "name": "山东玻纤",
        "change_pct": -5.66,
        "board": 1,
        "turnover": 11.43,
        "first_time": "",
        "amount": 15.6,
        "style": "换手"
      },
      {
        "code": "002354",
        "name": "天娱数科",
        "change_pct": -5.76,
        "board": 1,
        "turnover": 31.54,
        "first_time": "",
        "amount": 39.26,
        "style": "换手"
      },
      {
        "code": "603650",
        "name": "彤程新材",
        "change_pct": -6.03,
        "board": 1,
        "turnover": 7.07,
        "first_time": "",
        "amount": 27.55,
        "style": "换手"
      },
      {
        "code": "300709",
        "name": "精研科技",
        "change_pct": -6.5,
        "board": 1,
        "turnover": 17.94,
        "first_time": "",
        "amount": 12.98,
        "style": "换手"
      },
      {
        "code": "002585",
        "name": "双星新材",
        "change_pct": -6.6,
        "board": 1,
        "turnover": 19.3,
        "first_time": "",
        "amount": 20.52,
        "style": "换手"
      },
      {
        "code": "605069",
        "name": "正和生态",
        "change_pct": -7.62,
        "board": 1,
        "turnover": 8.97,
        "first_time": "",
        "amount": 2.05,
        "style": "换手"
      },
      {
        "code": "688126",
        "name": "沪硅产业",
        "change_pct": -9.2,
        "board": 1,
        "turnover": 9.54,
        "first_time": "",
        "amount": 83.16,
        "style": "换手"
      },
      {
        "code": "002669",
        "name": "康达新材",
        "change_pct": -9.87,
        "board": 1,
        "turnover": 19.02,
        "first_time": "",
        "amount": 9.23,
        "style": "换手"
      },
      {
        "code": "600403",
        "name": "大有能源",
        "change_pct": -9.94,
        "board": 1,
        "turnover": 3.82,
        "first_time": "",
        "amount": 6.62,
        "style": "换手"
      },
      {
        "code": "603155",
        "name": "新亚强",
        "change_pct": -9.99,
        "board": 1,
        "turnover": 9.5,
        "first_time": "",
        "amount": 7.04,
        "style": "换手"
      },
      {
        "code": "000636",
        "name": "风华高科",
        "change_pct": -10.0,
        "board": 1,
        "turnover": 14.15,
        "first_time": "",
        "amount": 99.98,
        "style": "换手"
      },
      {
        "code": "600378",
        "name": "XD昊华科",
        "change_pct": -10.0,
        "board": 1,
        "turnover": 10.37,
        "first_time": "",
        "amount": 66.18,
        "style": "换手"
      },
      {
        "code": "688530",
        "name": "欧莱新材",
        "change_pct": -12.62,
        "board": 1,
        "turnover": 28.13,
        "first_time": "",
        "amount": 12.35,
        "style": "换手"
      }
    ]
  },
  "limits": {
    "total_up": 94,
    "total_down": 9,
    "up_20cm": 8,
    "down_20cm": 0,
    "up_main_force": 39,
    "down_high": 4
  },
  "sectors": {
    "top5": [
      {
        "name": "贵金属",
        "change_pct": 5.65,
        "count_up": 13,
        "count_down": 0,
        "leader": "招金黄金",
        "leader_pct": 10.02
      },
      {
        "name": "工业金属",
        "change_pct": 5.62,
        "count_up": 53,
        "count_down": 1,
        "leader": "新威凌",
        "leader_pct": 29.95
      },
      {
        "name": "军工装备",
        "change_pct": 4.79,
        "count_up": 78,
        "count_down": 4,
        "leader": "通易航天",
        "leader_pct": 25.98
      },
      {
        "name": "机场航运",
        "change_pct": 4.27,
        "count_up": 13,
        "count_down": 0,
        "leader": "中信海直",
        "leader_pct": 9.98
      },
      {
        "name": "小金属",
        "change_pct": 4.26,
        "count_up": 26,
        "count_down": 3,
        "leader": "金钼股份",
        "leader_pct": 10.0
      }
    ],
    "bottom3": [
      {
        "name": "半导体",
        "change_pct": -0.47,
        "count_up": 75,
        "count_down": 100,
        "leader": "蓝箭电子",
        "leader_pct": 19.98
      },
      {
        "name": "非金属材料",
        "change_pct": -2.38,
        "count_up": 5,
        "count_down": 9,
        "leader": "平安电工",
        "leader_pct": 10.0
      },
      {
        "name": "电子化学品",
        "change_pct": -3.65,
        "count_up": 11,
        "count_down": 31,
        "leader": "光华科技",
        "leader_pct": 8.9
      }
    ]
  },
  "north_flow": 0,
  "dragon_tiger": [
    {
      "code": "000056",
      "name": "*ST皇庭",
      "change_pct": -5.2,
      "buy": 2352.7,
      "sell": 4826.98,
      "reason": "连续三个交易日内，跌幅偏离值累计达到12%的ST证券、*ST证券和未完成股改证券"
    },
    {
      "code": "000677",
      "name": "ST海龙",
      "change_pct": -4.23,
      "buy": 1318.13,
      "sell": 1905.02,
      "reason": "连续三个交易日内，跌幅偏离值累计达到12%的ST证券、*ST证券和未完成股改证券"
    },
    {
      "code": "000681",
      "name": "视觉中国",
      "change_pct": -9.98,
      "buy": 24285.64,
      "sell": 17539.1,
      "reason": "日跌幅偏离值达到7%的前5只证券"
    },
    {
      "code": "000759",
      "name": "中百集团",
      "change_pct": -6.19,
      "buy": 6188.9,
      "sell": 10646.7,
      "reason": "日振幅值达到15%的前5只证券"
    },
    {
      "code": "000823",
      "name": "超声电子",
      "change_pct": 6.88,
      "buy": 32324.47,
      "sell": 17771.35,
      "reason": "日振幅值达到15%的前5只证券"
    },
    {
      "code": "001210",
      "name": "金房能源",
      "change_pct": -2.28,
      "buy": 10316.62,
      "sell": 11226.5,
      "reason": "日振幅值达到15%的前5只证券"
    },
    {
      "code": "001696",
      "name": "宗申动力",
      "change_pct": 10.03,
      "buy": 62802.52,
      "sell": 24962.21,
      "reason": "日涨幅偏离值达到7%的前5只证券"
    },
    {
      "code": "001696",
      "name": "宗申动力",
      "change_pct": 10.03,
      "buy": 110387.54,
      "sell": 40345.28,
      "reason": "连续三个交易日内，涨幅偏离值累计达到20%的证券"
    },
    {
      "code": "002081",
      "name": "金螳螂",
      "change_pct": -9.93,
      "buy": 13262.99,
      "sell": 28475.48,
      "reason": "日跌幅偏离值达到7%的前5只证券"
    },
    {
      "code": "002082",
      "name": "ST万邦",
      "change_pct": -5.0,
      "buy": 5816.93,
      "sell": 5051.4,
      "reason": "连续三个交易日内，跌幅偏离值累计达到12%的ST证券、*ST证券和未完成股改证券"
    },
    {
      "code": "002119",
      "name": "康强电子",
      "change_pct": 10.01,
      "buy": 47828.75,
      "sell": 37158.13,
      "reason": "连续三个交易日内，涨幅偏离值累计达到20%的证券"
    },
    {
      "code": "002165",
      "name": "红宝丽",
      "change_pct": 10.0,
      "buy": 22854.36,
      "sell": 26835.81,
      "reason": "连续三个交易日内，涨幅偏离值累计达到20%的证券"
    },
    {
      "code": "002297",
      "name": "博云新材",
      "change_pct": 2.69,
      "buy": 40228.59,
      "sell": 29234.75,
      "reason": "日换手率达到20%的前5只证券"
    },
    {
      "code": "002354",
      "name": "天娱数科",
      "change_pct": -10.03,
      "buy": 22969.14,
      "sell": 16870.79,
      "reason": "日跌幅偏离值达到7%的前5只证券"
    },
    {
      "code": "002361",
      "name": "神剑股份",
      "change_pct": -8.53,
      "buy": 38530.18,
      "sell": 81712.71,
      "reason": "日换手率达到20%的前5只证券"
    },
    {
      "code": "002378",
      "name": "章源钨业",
      "change_pct": 10.01,
      "buy": 63946.55,
      "sell": 30730.17,
      "reason": "日涨幅偏离值达到7%的前5只证券"
    },
    {
      "code": "002407",
      "name": "多氟多",
      "change_pct": 9.99,
      "buy": 93830.43,
      "sell": 49894.6,
      "reason": "日涨幅偏离值达到7%的前5只证券"
    },
    {
      "code": "002409",
      "name": "雅克科技",
      "change_pct": 10.0,
      "buy": 78266.79,
      "sell": 79434.93,
      "reason": "日涨幅偏离值达到7%的前5只证券"
    },
    {
      "code": "002409",
      "name": "雅克科技",
      "change_pct": 10.0,
      "buy": 113857.71,
      "sell": 100043.82,
      "reason": "连续三个交易日内，涨幅偏离值累计达到20%的证券"
    },
    {
      "code": "002428",
      "name": "云南锗业",
      "change_pct": 10.0,
      "buy": 175841.92,
      "sell": 82277.19,
      "reason": "日涨幅偏离值达到7%的前5只证券"
    },
    {
      "code": "002514",
      "name": "*ST宝馨",
      "change_pct": -4.89,
      "buy": 5012.99,
      "sell": 5595.18,
      "reason": "连续三个交易日内，跌幅偏离值累计达到12%的ST证券、*ST证券和未完成股改证券"
    },
    {
      "code": "002552",
      "name": "宝鼎科技",
      "change_pct": -10.0,
      "buy": 14343.53,
      "sell": 13471.68,
      "reason": "日跌幅偏离值达到7%的前5只证券"
    },
    {
      "code": "002581",
      "name": "*ST未名",
      "change_pct": -3.02,
      "buy": 3066.27,
      "sell": 3160.48,
      "reason": "连续三个交易日内，跌幅偏离值累计达到12%的ST证券、*ST证券和未完成股改证券"
    },
    {
      "code": "002585",
      "name": "双星新材",
      "change_pct": -7.45,
      "buy": 38458.84,
      "sell": 54917.46,
      "reason": "日换手率达到20%的前5只证券"
    },
    {
      "code": "002667",
      "name": "*ST威领",
      "change_pct": -4.98,
      "buy": 1442.57,
      "sell": 3898.98,
      "reason": "连续三个交易日内，跌幅偏离值累计达到12%的ST证券、*ST证券和未完成股改证券"
    },
    {
      "code": "002735",
      "name": "王子新材",
      "change_pct": 2.54,
      "buy": 21465.78,
      "sell": 23181.41,
      "reason": "日换手率达到20%的前5只证券"
    },
    {
      "code": "002896",
      "name": "中大力德",
      "change_pct": -10.0,
      "buy": 20127.76,
      "sell": 18098.12,
      "reason": "日跌幅偏离值达到7%的前5只证券"
    },
    {
      "code": "003026",
      "name": "中晶科技",
      "change_pct": -1.91,
      "buy": 12028.19,
      "sell": 14548.49,
      "reason": "日换手率达到20%的前5只证券"
    },
    {
      "code": "300263",
      "name": "隆华科技",
      "change_pct": 19.97,
      "buy": 44820.9,
      "sell": 31063.91,
      "reason": "日涨幅达到15%的前5只证券"
    },
    {
      "code": "300264",
      "name": "佳创视讯",
      "change_pct": 17.45,
      "buy": 18340.18,
      "sell": 14495.4,
      "reason": "连续三个交易日内，涨幅偏离值累计达到30%的证券"
    }
  ],
  "events": [
    {
      "time": "05:48",
      "type": "blast",
      "msg": "永冠新材 炸板"
    },
    {
      "time": "05:48",
      "type": "blast",
      "msg": "露笑科技 炸板"
    },
    {
      "time": "05:48",
      "type": "blast",
      "msg": "风语筑 炸板"
    },
    {
      "time": "05:48",
      "type": "blast",
      "msg": "仙鹤股份 炸板"
    },
    {
      "time": "05:48",
      "type": "blast",
      "msg": "焦作万方 炸板"
    },
    {
      "time": "05:48",
      "type": "blast",
      "msg": "云南铜业 炸板"
    },
    {
      "time": "05:48",
      "type": "blast",
      "msg": "江西铜业 炸板"
    },
    {
      "time": "05:48",
      "type": "blast",
      "msg": "中国稀土 炸板"
    },
    {
      "time": "05:48",
      "type": "blast",
      "msg": "盛屯矿业 炸板"
    },
    {
      "time": "05:48",
      "type": "blast",
      "msg": "S佳通 炸板"
    },
    {
      "time": "05:48",
      "type": "blast",
      "msg": "光华科技 炸板"
    },
    {
      "time": "05:48",
      "type": "blast",
      "msg": "飞南资源 炸板"
    },
    {
      "time": "05:48",
      "type": "blast",
      "msg": "衢州发展 炸板"
    },
    {
      "time": "05:48",
      "type": "blast",
      "msg": "武进不锈 炸板"
    },
    {
      "time": "05:48",
      "type": "blast",
      "msg": "财达证券 炸板"
    },
    {
      "time": "05:48",
      "type": "blast",
      "msg": "孚日股份 炸板"
    },
    {
      "time": "05:48",
      "type": "blast",
      "msg": "剑桥科技 炸板"
    },
    {
      "time": "05:48",
      "type": "blast",
      "msg": "苏博特 炸板"
    },
    {
      "time": "05:48",
      "type": "blast",
      "msg": "迪安诊断 炸板"
    },
    {
      "time": "05:48",
      "type": "blast",
      "msg": "深桑达Ａ 炸板"
    },
    {
      "time": "05:48",
      "type": "blast",
      "msg": "深圳新星 炸板"
    },
    {
      "time": "05:48",
      "type": "limit_down",
      "msg": "新亚强 跌停"
    },
    {
      "time": "05:48",
      "type": "limit_down",
      "msg": "达实智能 跌停"
    },
    {
      "time": "05:48",
      "type": "limit_down",
      "msg": "三孚股份 跌停"
    },
    {
      "time": "05:48",
      "type": "limit_down",
      "msg": "五方光电 跌停"
    },
    {
      "time": "05:48",
      "type": "limit_down",
      "msg": "沃格光电 跌停"
    },
    {
      "time": "05:48",
      "type": "limit_down",
      "msg": "大有能源 跌停"
    },
    {
      "time": "05:48",
      "type": "limit_down",
      "msg": "京能置业 跌停"
    },
    {
      "time": "05:48",
      "type": "limit_down",
      "msg": "XD昊华科 跌停"
    },
    {
      "time": "05:48",
      "type": "limit_down",
      "msg": "风华高科 跌停"
    }
  ],
  "history_emotion": [
    {
      "date": "2026-06-02",
      "score": 79
    }
  ]
}